roast_my_stuff/__init__.py
roast_my_stuff-0.1.0.dist-info/METADATA
roast_my_stuff-0.1.0.dist-info/WHEEL
roast_my_stuff-0.1.0.dist-info/entry_points.txt
roast_my_stuff-0.1.0.dist-info/RECORD
