Metadata-Version: 2.4
Name: roast-my-stuff
Version: 0.1.0
Summary: A CLI tool to roast your OS, software, and hardware.
Requires-Python: >=3.8
Requires-Dist: openai>=1.60.1
Requires-Dist: rich>=13.9.4
